bob_telegram_tools/InlineMenuBot.py
bob_telegram_tools/__init__.py
bob_telegram_tools/bot.py
bob_telegram_tools/keras.py
bob_telegram_tools/utils.py
bob_telegram_tools-1.1.0.dist-info/LICENCE
bob_telegram_tools-1.1.0.dist-info/METADATA
bob_telegram_tools-1.1.0.dist-info/WHEEL
bob_telegram_tools-1.1.0.dist-info/top_level.txt
bob_telegram_tools-1.1.0.dist-info/RECORD
