Metadata-Version: 2.1
Name: bob-telegram-tools
Version: 1.1.0
Summary: A package to monitor your Machine Learning trainings every where without any additional app.
Home-page: https://github.com/robertanto/bob_telegram_tools
Author: Antonio Roberto
Author-email: roberto.antonio@outlook.it
License: UNKNOWN
Platform: UNKNOWN
Classifier: Programming Language :: Python :: 3
Classifier: License :: OSI Approved :: GNU General Public License v3 or later (GPLv3+)
Classifier: Operating System :: OS Independent
Requires-Python: >=3.6
